apiverve_cardvalidator/__init__.py
apiverve_cardvalidator/apiClient.py
apiverve_cardvalidator/exceptions.py
apiverve_cardvalidator/setup.py
apiverve_cardvalidator/setup_dep.py
apiverve_cardvalidator/tests/__init__.py
apiverve_cardvalidator/tests/test_api.py
apiverve_cardvalidator-1.1.8.dist-info/LICENSE
apiverve_cardvalidator-1.1.8.dist-info/METADATA
apiverve_cardvalidator-1.1.8.dist-info/WHEEL
apiverve_cardvalidator-1.1.8.dist-info/top_level.txt
apiverve_cardvalidator-1.1.8.dist-info/RECORD
